{"type":"FeatureCollection","features":[{"type":"Feature","geometry":{"type":"Point","coordinates":[30.1266,60.8393]},"properties":{"time":1530782892}},{"type":"Feature","geometry":{"type":"Point","coordinates":[29.8533,60.8885]},"properties":{"time":1530782892}},{"type":"Feature","geometry":{"type":"Point","coordinates":[30.0404,60.8177]},"properties":{"time":1530782892}},{"type":"Feature","geometry":{"type":"Point","coordinates":[30.0867,60.8067]},"properties":{"time":1530782983}},{"type":"Feature","geometry":{"type":"Point","coordinates":[29.888,60.9141]},"properties":{"time":1530783234}},{"type":"Feature","geometry":{"type":"Point","coordinates":[27.5832,60.8052]},"properties":{"time":1530787155}},{"type":"Feature","geometry":{"type":"Point","coordinates":[27.6358,60.8286]},"properties":{"time":1530787155}},{"type":"Feature","geometry":{"type":"Point","coordinates":[29.1129,60.6795]},"properties":{"time":1530787273}},{"type":"Feature","geometry":{"type":"Point","coordinates":[29.2338,60.6338]},"properties":{"time":1530787273}},{"type":"Feature","geometry":{"type":"Point","coordinates":[29.033,60.6646]},"properties":{"time":1530787273}},{"type":"Feature","geometry":{"type":"Point","coordinates":[29.1799,60.6548]},"properties":{"time":1530787273}},{"type":"Feature","geometry":{"type":"Point","coordinates":[29.2786,60.6746]},"properties":{"time":1530787803}},{"type":"Feature","geometry":{"type":"Point","coordinates":[29.0979,60.6724]},"properties":{"time":1530788114}},{"type":"Feature","geometry":{"type":"Point","coordinates":[29.1905,60.6594]},"properties":{"time":1530788200}},{"type":"Feature","geometry":{"type":"Point","coordinates":[28.9948,60.6598]},"properties":{"time":1530788481}},{"type":"Feature","geometry":{"type":"Point","coordinates":[29.0031,60.6833]},"properties":{"time":1530788481}},{"type":"Feature","geometry":{"type":"Point","coordinates":[28.3085,60.5831]},"properties":{"time":1530790354}},{"type":"Feature","geometry":{"type":"Point","coordinates":[28.2172,60.5674]},"properties":{"time":1530790479}},{"type":"Feature","geometry":{"type":"Point","coordinates":[28.0006,60.8935]},"properties":{"time":1530791148}},{"type":"Feature","geometry":{"type":"Point","coordinates":[28.2587,60.555]},"properties":{"time":1530791148}},{"type":"Feature","geometry":{"type":"Point","coordinates":[27.8001,60.5303]},"properties":{"time":1530791509}},{"type":"Feature","geometry":{"type":"Point","coordinates":[30.3524,60.3779]},"properties":{"time":1530792097}},{"type":"Feature","geometry":{"type":"Point","coordinates":[30.4979,60.3584]},"properties":{"time":1530792957}},{"type":"Feature","geometry":{"type":"Point","coordinates":[30.5413,60.339]},"properties":{"time":1530792957}},{"type":"Feature","geometry":{"type":"Point","coordinates":[25.6912,60.4498]},"properties":{"time":1530793876}},{"type":"Feature","geometry":{"type":"Point","coordinates":[25.6937,60.4229]},"properties":{"time":1530793876}},{"type":"Feature","geometry":{"type":"Point","coordinates":[25.7363,60.3509]},"properties":{"time":1530794206}},{"type":"Feature","geometry":{"type":"Point","coordinates":[25.7198,60.4078]},"properties":{"time":1530794206}},{"type":"Feature","geometry":{"type":"Point","coordinates":[25.6565,60.4108]},"properties":{"time":1530794335}}]}